bbdr_morpheme/__init__.py
bbdr_morpheme/bbdr_morpheme.py
bbdr_morpheme/data/apt.dic
bbdr_morpheme/data/dask_apt_20.csv.parquet
bbdr_morpheme/data/stop_words.csv
bbdr_morpheme-0.0.2.dist-info/LICENSE
bbdr_morpheme-0.0.2.dist-info/METADATA
bbdr_morpheme-0.0.2.dist-info/WHEEL
bbdr_morpheme-0.0.2.dist-info/entry_points.txt
bbdr_morpheme-0.0.2.dist-info/top_level.txt
bbdr_morpheme-0.0.2.dist-info/RECORD
