Metadata-Version: 2.1
Name: bbdr-morpheme
Version: 0.0.2
Summary: BBDR - korean morpheme parse from parquet file.
Home-page: http://www.bbdr.co.kr/
Author: ttajun
Author-email: ttajun@bbdr.co.kr
License: UNKNOWN
Download-URL: http://www.bbdr.co.kr/
Keywords: bbdr korean morpheme
Platform: UNKNOWN
Classifier: Programming Language :: Python :: 3.7
Classifier: License :: OSI Approved :: MIT License
Classifier: Operating System :: OS Independent
Requires-Python: >=3.7
Requires-Dist: dask
Requires-Dist: konlpy
Requires-Dist: pandas
Requires-Dist: pyarrow
Requires-Dist: tweepy (==3.10.0)
